everycure/__init__.py
everycure/datasets/__init__.py
everycure/datasets/cli.py
everycure/datasets/generate_schema.py
everycure/datasets/validate.py
everycure/datasets/kedro/__init__.py
everycure/datasets/kedro/catalog_dataset.py
everycure/datasets/kedro/hooks.py
everycure/datasets/kedro/storage.py
everycure/datasets/models/__init__.py
everycure/datasets/models/v1.py
everycure/datasets/models/v2.py
everycure_datasets-0.2.37.dist-info/METADATA
everycure_datasets-0.2.37.dist-info/WHEEL
everycure_datasets-0.2.37.dist-info/entry_points.txt
everycure_datasets-0.2.37.dist-info/RECORD
