Metadata-Version: 2.4
Name: everycure-datasets
Version: 0.2.37
Requires-Python: >=3.11
Requires-Dist: gitpython>=3.1.45
Requires-Dist: google-api-core>=2.28.1
Requires-Dist: google-cloud-bigquery>=3.17.0
Requires-Dist: pydantic>=2.0.0
Requires-Dist: pyyaml>=6.0.0
Provides-Extra: kedro
Requires-Dist: kedro-datasets[pandas,spark]>=6.0.0; extra == 'kedro'
Requires-Dist: kedro>=0.19.1; extra == 'kedro'
Requires-Dist: semantic-version>=2.10.0; extra == 'kedro'
